pygranta/__init__.py
pygranta-2025.2.1.dist-info/AUTHORS
pygranta-2025.2.1.dist-info/LICENSE
pygranta-2025.2.1.dist-info/METADATA
pygranta-2025.2.1.dist-info/WHEEL
pygranta-2025.2.1.dist-info/RECORD
