Metadata-Version: 2.3
Name: pygranta
Version: 2025.2.1
Summary: Pythonic interfaces to Ansys Granta MI
License: MIT
Author: ANSYS, Inc.
Author-email: pyansys.core@ansys.com
Maintainer: ANSYS, Inc.
Maintainer-email: pyansys.core@ansys.com
Requires-Python: >=3.10,<4.0
Classifier: Development Status :: 5 - Production/Stable
Classifier: Intended Audience :: Science/Research
Classifier: License :: OSI Approved :: MIT License
Classifier: Operating System :: OS Independent
Classifier: Programming Language :: Python :: 3
Classifier: Programming Language :: Python :: 3.10
Classifier: Programming Language :: Python :: 3.11
Classifier: Programming Language :: Python :: 3.12
Classifier: Programming Language :: Python :: 3.13
Classifier: Topic :: Scientific/Engineering :: Information Analysis
Requires-Dist: ansys-grantami-bomanalytics (==2.3.1)
Requires-Dist: ansys-grantami-bomanalytics-openapi (==4.0.0)
Requires-Dist: ansys-grantami-dataflow-extensions (==0.2.0) ; sys_platform == "win32"
Requires-Dist: ansys-grantami-jobqueue (==1.2.0)
Requires-Dist: ansys-grantami-recordlists (==2.0.1)
Requires-Dist: ansys-grantami-serverapi-openapi (==5.0.0)
Project-URL: Documentation, https://grantami.docs.pyansys.com
Project-URL: Repository, https://github.com/ansys/pygranta
